odoo/addons/partner_prospect/README.rst
odoo/addons/partner_prospect/__init__.py
odoo/addons/partner_prospect/__manifest__.py
odoo/addons/partner_prospect/i18n/ca.po
odoo/addons/partner_prospect/i18n/de.po
odoo/addons/partner_prospect/i18n/es.po
odoo/addons/partner_prospect/i18n/fr.po
odoo/addons/partner_prospect/i18n/partner_prospect.pot
odoo/addons/partner_prospect/i18n/sl.po
odoo/addons/partner_prospect/models/__init__.py
odoo/addons/partner_prospect/models/res_partner.py
odoo/addons/partner_prospect/static/description/icon.png
odoo/addons/partner_prospect/tests/__init__.py
odoo/addons/partner_prospect/tests/test_partner_prospect.py
odoo/addons/partner_prospect/views/res_partner_view.xml
odoo11_addon_partner_prospect-11.0.1.0.0.99.dev6.dist-info/METADATA
odoo11_addon_partner_prospect-11.0.1.0.0.99.dev6.dist-info/WHEEL
odoo11_addon_partner_prospect-11.0.1.0.0.99.dev6.dist-info/top_level.txt
odoo11_addon_partner_prospect-11.0.1.0.0.99.dev6.dist-info/RECORD
